{
  "version": 3,
  "middleware": {
    "/": {
      "files": [
        "server/edge-runtime-webpack.js",
        "server/middleware.js"
      ],
      "name": "middleware",
      "page": "/",
      "matchers": [
        {
          "regexp": "^(?:\\/(_next\\/data\\/[^/]{1,}))?(?:\\/((?!.+\\.[\\w]+$|_next).*))(\\.json)?[\\/#\\?]?$",
          "originalSource": "/((?!.+\\.[\\w]+$|_next).*)"
        },
        {
          "regexp": "^(?:\\/(_next\\/data\\/[^/]{1,}))?(?:\\/(\\/?index|\\/?index\\.json))?[\\/#\\?]?$",
          "originalSource": "/"
        },
        {
          "regexp": "^(?:\\/(_next\\/data\\/[^/]{1,}))?(?:\\/(api|trpc))(.*)(\\.json)?[\\/#\\?]?$",
          "originalSource": "/(api|trpc)(.*)"
        }
      ],
      "wasm": [],
      "assets": [],
      "env": {
        "__NEXT_BUILD_ID": "t9JZ-e7vNQ04E2xGqx-L3",
        "NEXT_SERVER_ACTIONS_ENCRYPTION_KEY": "SV8Ir3rzBaht0hI1IjuaFGta2aEzUViqS9gHwonPF4w=",
        "__NEXT_PREVIEW_MODE_ID": "2b205fe914e33bfa78cf367c807603f0",
        "__NEXT_PREVIEW_MODE_SIGNING_KEY": "ee43f5ae4f81670baa03310cf5aa98c540abe64a40691ea8adb64331482664f9",
        "__NEXT_PREVIEW_MODE_ENCRYPTION_KEY": "1aa6aa235a83186fdc8e3dfb95464dce5e4a99e9ecc5e36de837f9896a2d9d06"
      }
    }
  },
  "functions": {},
  "sortedMiddleware": [
    "/"
  ]
}